crabs/__init__.py
crabs/__version__.py
crabs/crabs.py
crabs/module_assign_tax.py
crabs/module_db_cleanup.py
crabs/module_db_download.py
crabs/module_visualizations.py
crabs-0.2.0.dist-info/LICENSE
crabs-0.2.0.dist-info/METADATA
crabs-0.2.0.dist-info/WHEEL
crabs-0.2.0.dist-info/entry_points.txt
crabs-0.2.0.dist-info/top_level.txt
crabs-0.2.0.dist-info/RECORD
